LICENSE
README.md
setup.py
sangreal_wind/__init__.py
sangreal_wind.egg-info/PKG-INFO
sangreal_wind.egg-info/SOURCES.txt
sangreal_wind.egg-info/dependency_links.txt
sangreal_wind.egg-info/requires.txt
sangreal_wind.egg-info/top_level.txt
sangreal_wind/api/__init__.py
sangreal_wind/api/get_fund_data.py
sangreal_wind/api/get_fund_list.py
sangreal_wind/api/get_index_data.py
sangreal_wind/api/get_index_weight.py
sangreal_wind/api/get_industry.py
sangreal_wind/api/get_ret.py
sangreal_wind/api/get_universe.py
sangreal_wind/crawler/__init__.py
sangreal_wind/crawler/futures/__init__.py
sangreal_wind/crawler/futures/domestic.py
sangreal_wind/crawler/futures/domestic_cons.py
sangreal_wind/hk_sangreal_calendar/__init__.py
sangreal_wind/sangreal_calendar/__init__.py
sangreal_wind/utils/__init__.py
sangreal_wind/utils/commons.py
sangreal_wind/utils/datetime_handle.py
sangreal_wind/utils/engines.py
sangreal_wind/utils/fund_type.py